scrapy_cloudflare_middleware/__init__.py
scrapy_cloudflare_middleware/middlewares.py
scrapy_cloudflare_middleware-0.0.1.dist-info/DESCRIPTION.rst
scrapy_cloudflare_middleware-0.0.1.dist-info/METADATA
scrapy_cloudflare_middleware-0.0.1.dist-info/RECORD
scrapy_cloudflare_middleware-0.0.1.dist-info/WHEEL
scrapy_cloudflare_middleware-0.0.1.dist-info/metadata.json
scrapy_cloudflare_middleware-0.0.1.dist-info/top_level.txt
