Metadata-Version: 1.0
Name: scrapy-cloudflare-middleware
Version: 0.0.1
Summary: A Scrapy Middleware to bypass the CloudFlare's anti-bot protection
Home-page: https://github.com/clemfromspace/scrapy-cloudflare-middleware
Author: UNKNOWN
Author-email: UNKNOWN
License: UNKNOWN
Platform: UNKNOWN
